TensorflowZhinengYidongXiangmuChuyi/README.md
TensorflowZhinengYidongXiangmuChuyi/__init__.py
TensorflowZhinengYidongXiangmuChuyi/__main__.py
TensorflowZhinengYidongXiangmuChuyi/file.epub
TensorflowZhinengYidongXiangmuChuyi/index.html
TensorflowZhinengYidongXiangmuChuyi/css/__init__.py
TensorflowZhinengYidongXiangmuChuyi/css/annotations.css
TensorflowZhinengYidongXiangmuChuyi/css/main.css
TensorflowZhinengYidongXiangmuChuyi/css/normalize.css
TensorflowZhinengYidongXiangmuChuyi/css/popup.css
TensorflowZhinengYidongXiangmuChuyi/font/__init__.py
TensorflowZhinengYidongXiangmuChuyi/font/fontello.eot
TensorflowZhinengYidongXiangmuChuyi/font/fontello.svg
TensorflowZhinengYidongXiangmuChuyi/font/fontello.ttf
TensorflowZhinengYidongXiangmuChuyi/font/fontello.woff
TensorflowZhinengYidongXiangmuChuyi/img/__init__.py
TensorflowZhinengYidongXiangmuChuyi/img/annotator-glyph-sprite.png
TensorflowZhinengYidongXiangmuChuyi/img/annotator-icon-sprite.png
TensorflowZhinengYidongXiangmuChuyi/img/apple-touch-icon.png
TensorflowZhinengYidongXiangmuChuyi/img/cancelfullscreen.png
TensorflowZhinengYidongXiangmuChuyi/img/close.png
TensorflowZhinengYidongXiangmuChuyi/img/fullscreen.png
TensorflowZhinengYidongXiangmuChuyi/img/loader.gif
TensorflowZhinengYidongXiangmuChuyi/img/menu-icon.png
TensorflowZhinengYidongXiangmuChuyi/img/save.png
TensorflowZhinengYidongXiangmuChuyi/img/saved.png
TensorflowZhinengYidongXiangmuChuyi/img/settings-s.png
TensorflowZhinengYidongXiangmuChuyi/img/settings.png
TensorflowZhinengYidongXiangmuChuyi/img/star.png
TensorflowZhinengYidongXiangmuChuyi/js/__init__.py
TensorflowZhinengYidongXiangmuChuyi/js/epub.js
TensorflowZhinengYidongXiangmuChuyi/js/epub.min.js
TensorflowZhinengYidongXiangmuChuyi/js/epub.min.map
TensorflowZhinengYidongXiangmuChuyi/js/hooks.min.js
TensorflowZhinengYidongXiangmuChuyi/js/hooks.min.map
TensorflowZhinengYidongXiangmuChuyi/js/reader.js
TensorflowZhinengYidongXiangmuChuyi/js/reader.js.map
TensorflowZhinengYidongXiangmuChuyi/js/reader.min.js
tensorflow_zhineng_yidong_xiangmu_chuyi-2024.3.5.0.dist-info/METADATA
tensorflow_zhineng_yidong_xiangmu_chuyi-2024.3.5.0.dist-info/WHEEL
tensorflow_zhineng_yidong_xiangmu_chuyi-2024.3.5.0.dist-info/entry_points.txt
tensorflow_zhineng_yidong_xiangmu_chuyi-2024.3.5.0.dist-info/top_level.txt
tensorflow_zhineng_yidong_xiangmu_chuyi-2024.3.5.0.dist-info/RECORD
